hnscraper/__init__.py
hnscraper/hacker_news_scraper.py
hnscraper/main.py
hnscraper/py.typed
hnscraper-0.1.0.dist-info/entry_points.txt
hnscraper-0.1.0.dist-info/LICENSE
hnscraper-0.1.0.dist-info/WHEEL
hnscraper-0.1.0.dist-info/METADATA
hnscraper-0.1.0.dist-info/RECORD
