Metadata-Version: 2.1
Name: hnscraper
Version: 0.1.0
Summary: Hackernews Scraper
Home-page: https://github.com/pushp1997/Hackernews-Scraping/
License: MIT
Author: Pushp Vashisht
Author-email: pushptyagi1@gmail.com
Requires-Python: >=3.7,<4
Classifier: License :: OSI Approved :: MIT License
Classifier: Programming Language :: Python :: 3
Classifier: Programming Language :: Python :: 3.10
Classifier: Programming Language :: Python :: 3.7
Classifier: Programming Language :: Python :: 3.8
Classifier: Programming Language :: Python :: 3.9
Requires-Dist: BeautifulSoup4 (>=4.11.1,<5.0.0)
Requires-Dist: jupyterlab (>=3.4.3,<4.0.0)
Requires-Dist: notebook (>=6.4.12,<7.0.0)
Requires-Dist: pathlib (>=1.0.1,<2.0.0)
Requires-Dist: pymongo (>=4.1.1,<5.0.0)
Requires-Dist: requests (>=2.28.0,<3.0.0)
Project-URL: Repository, https://github.com/pushp1997/Hackernews-Scraping/
